[
    {
        "page": 2,
        "label": 16,
        "rect": [
            131.00568063787824,
            85.73606431227464,
            252.05712361592182,
            229.1792294546274
        ]
    },
    {
        "page": 3,
        "label": 22,
        "rect": [
            151.68747523374068,
            68.64641657902644,
            225.98007825592134,
            179.60320312500002
        ]
    },
    {
        "page": 3,
        "label": 23,
        "rect": [
            120.21517910960218,
            396.0480889423077,
            261.9484166835082,
            521.3961577899639
        ]
    },
    {
        "page": 3,
        "label": 24,
        "rect": [
            344.1180858213304,
            72.2442371544471,
            511.02916029454724,
            216.48086402306188
        ]
    },
    {
        "page": 3,
        "label": 25,
        "rect": [
            358.50542119236513,
            373.5617103459285,
            493.9441995414434,
            509.70324091984673
        ]
    },
    {
        "page": 4,
        "label": 26,
        "rect": [
            118.41676218822283,
            68.64641657902644,
            263.7468336048875,
            201.19012657752404
        ]
    },
    {
        "page": 4,
        "label": 27,
        "rect": [
            113.92071988477447,
            372.6622552020733,
            268.2428759083359,
            454.8364771446815
        ]
    },
    {
        "page": 4,
        "label": 28,
        "rect": [
            361.2030465744341,
            72.2442371544471,
            494.8434080021331,
            191.29611999511718
        ]
    },
    {
        "page": 4,
        "label": 30,
        "rect": [
            335.1260012144337,
            513.8767127873348,
            519.1220364407542,
            707.5833725679838
        ]
    },
    {
        "page": 6,
        "label": 40,
        "rect": [
            140.89697370546463,
            530.966360520583,
            243.06503900902507,
            615.8389478947566
        ]
    },
    {
        "page": 6,
        "label": 41,
        "rect": [
            386.380883473745,
            101.02680175781249,
            468.76636264213266,
            207.48631258451022
        ]
    },
    {
        "page": 6,
        "label": 42,
        "rect": [
            333.32758429305426,
            481.49632760854865,
            525.4164956655819,
            605.0454861684946
        ]
    },
    {
        "page": 7,
        "label": 45,
        "rect": [
            109.42467758132612,
            488.69196875939,
            270.04129282971525,
            635.6269610595704
        ]
    },
    {
        "page": 7,
        "label": "47a",
        "rect": [
            345.9165027427097,
            215.2576050274189,
            428.3019819110974,
            298.1410895244892
        ]
    },
    {
        "page": 7,
        "label": "47b",
        "rect": [
            436.73655727236655,
            208.9614190204327,
            508.3315349124782,
            298.1410895244892
        ]
    },
    {
        "page": 7,
        "label": 48,
        "rect": [
            353.1101704282271,
            495.8876099102314,
            502.0370756876505,
            579.8607421405499
        ]
    },
    {
        "page": 8,
        "label": 49,
        "rect": [
            104.92863527787775,
            72.2442371544471,
            278.13416897592225,
            188.5977545635517
        ]
    },
    {
        "page": 8,
        "label": 50,
        "rect": [
            116.61834526684348,
            360.9693383319561,
            266.44445898695653,
            468.328304302509
        ]
    },
    {
        "page": 8,
        "label": 51,
        "rect": [
            382.7840496309862,
            72.2442371544471,
            472.3631964848914,
            196.6928508582482
        ]
    },
    {
        "page": 8,
        "label": "52a",
        "rect": [
            365.69908887788245,
            350.1758766056941,
            516.4244110586852,
            441.344649986854
        ]
    },
    {
        "page": 8,
        "label": "52b",
        "rect": [
            376.4895904061585,
            477.898507033128,
            502.9362841483401,
            614.0400376070463
        ]
    },
    {
        "page": 9,
        "label": "52c",
        "rect": [
            121.11438757029185,
            72.2442371544471,
            286.2270451221293,
            173.30701711801385
        ]
    },
    {
        "page": 9,
        "label": 53,
        "rect": [
            127.40884679511954,
            349.27642146183894,
            255.65395745868048,
            464.7304837270883
        ]
    },
    {
        "page": 9,
        "label": 54,
        "rect": [
            350.4125450461581,
            72.2442371544471,
            505.63390953040914,
            188.5977545635517
        ]
    }
]