[
    {
        "page": 2,
        "label": "5",
        "rect": [
            303.06,
            231.67,
            496.39,
            378.33
        ]
    },
    {
        "page": 4,
        "label": "15",
        "rect": [
            348.06,
            623.33,
            494.72,
            776.67
        ]
    },
    {
        "page": 5,
        "label": "16",
        "rect": [
            296.39,
            88.33,
            504.72,
            235
        ]
    },
    {
        "page": 5,
        "label": "17",
        "rect": [
            254.72,
            335,
            503.06,
            485
        ]
    },
    {
        "page": 5,
        "label": "18",
        "rect": [
            296.39,
            595,
            504.72,
            771.67
        ]
    },
    {
        "page": 6,
        "label": "20",
        "rect": [
            301.39,
            296.67,
            491.39,
            485
        ]
    },
    {
        "page": 6,
        "label": "21",
        "rect": [
            288.06,
            576.67,
            494.72,
            761.67
        ]
    },
    {
        "page": 8,
        "label": "25",
        "rect": [
            231.39,
            91.67,
            511.39,
            258.33
        ]
    },
    {
        "page": 9,
        "label": "29",
        "rect": [
            314.72,
            276.67,
            498.06,
            456.67
        ]
    },
    {
        "page": 9,
        "label": "30",
        "rect": [
            128.06,
            511.67,
            343.06,
            575
        ]
    },
    {
        "page": 10,
        "label": "32",
        "rect": [
            274.72,
            371.67,
            498.06,
            543.33
        ]
    },
    {
        "page": 12,
        "label": "38a",
        "rect": [
            111.39,
            105,
            254.72,
            261.67
        ]
    },
    {
        "page": 12,
        "label": "38b",
        "rect": [
            308.06,
            105,
            461.39,
            261.67
        ]
    },
    {
        "page": 12,
        "label": "38c",
        "rect": [
            109.72,
            291.67,
            251.39,
            448.33
        ]
    },
    {
        "page": 12,
        "label": "38d",
        "rect": [
            304.72,
            291.67,
            464.72,
            451.67
        ]
    },
    {
        "page": 13,
        "label": "40",
        "rect": [
            289.72,
            95,
            513.06,
            271.67
        ]
    },
    {
        "page": 13,
        "label": "41",
        "rect": [
            276.39,
            361.11,
            493.06,
            524.44
        ]
    }
]