[{"statement": "If \\(r=\\sqrt[3]{h^3-7r^3}\\), then the ratio \\(r:h\\) is", "options": ["\\(1:8\\).", "\\(1:2\\sqrt{2}\\).", "\\(1:2\\).", "\\(1:\\sqrt{2}\\).", "\\(1:\\sqrt[3]{2}\\)."]}, {"statement": "\\(\\dfrac{\\dfrac{x^2}{3}-3y^2}{\\dfrac{3}{2}(x-3y)}=\\)", "options": ["\\(\\dfrac{1}{2}(x-3y)\\).", "\\(\\dfrac{2}{9}(x-3y)\\).", "\\(2(x+3y)\\).", "\\(\\dfrac{1}{2}(x+3y)\\).", "\\(\\dfrac{2}{9}(x+3y)\\)."]}, {"statement": "If \\(1-\\dfrac{x+y}{y-x}=a\\) (\\(a\\neq0\\)), then \\(y=\\)", "options": ["\\(x\\).", "\\(\\dfrac{x}{a}(a-2)\\).", "\\(\\dfrac{x}{a}(a-1)\\).", "\\(\\dfrac{x}{a}(2-a)\\).", "\\(\\dfrac{x}{a}(1-a)\\)."]}, {"statement": "Which of the following is an identity/are identities?<br/>I. \\((x+1)(x-1)=x^2+1\\),<br/>II. \\(x^2-2x+1=0\\),<br/>III. \\((x-2)^2=(2-x)^2\\).", "options": ["I only", "II only", "III only", "I and II only", "I and III only"]}, {"statement": "Given the identity \\(\\dfrac{2}{x-1}+\\dfrac{x+1}{(x-1)^2}+\\dfrac{a}{(1-x)^2} \\equiv \\dfrac{bx-2}{(x-1)^2}\\), find the values of the constants \\(a\\) and \\(b\\).", "options": ["\\(a=1, b=3\\)", "\\(a=3, b=1\\)", "\\(a=1, b=-3\\)", "\\(a=3, b=-1\\)", "\\(a=-1, b=3\\)"]}, {"statement": "If \\(\\alpha\\) and \\(\\beta\\) are the roots of the equation \\(2x^2+x+3=0\\), find the value of \\(\\alpha-\\dfrac{\\alpha^2}{\\alpha+\\beta}\\).", "options": ["\\(-3\\)", "\\(-2\\)", "\\(2\\)", "\\(3\\)", "It cannot be determined"]}, {"statement": "<img alt=\"Figure 7\" src=\"artifact/paper-2/1986/figure/7.svg\"/><br/>The figure shows an infinite number of squares. The length of a side of the first square is \\(1\\). The side of the first square is equal to half of the side of the preceding one. Find the sum of the areas of the infinite number of squares.", "options": ["\\(4\\)", "\\(2\\)", "\\(\\dfrac{5}{3}\\)", "\\(\\dfrac{3}{2}\\)", "\\(\\dfrac{4}{3}\\)"]}, {"statement": "Find the real value of \\(x\\) such that \\(\\begin{cases} x^2+x+1=k \\\\ x-1=\\dfrac{7}{k} \\end{cases}\\), where \\(k\\) is a constant.", "options": ["\\(3\\)", "\\(2\\)", "\\(1\\)", "\\(-1\\)", "\\(-3\\)"]}, {"statement": "<img alt=\"Figure 9a\" src=\"artifact/paper-2/1986/figure/9a.svg\"/> <img alt=\"Figure 9b\" src=\"artifact/paper-2/1986/figure/9b.svg\"/><br/>The figure shows two sectors with radii \\(r\\) and \\(2r\\). If these two sectors are equal in area, then \\(\\theta_1:\\theta_2=\\)", "options": ["\\(2:1\\).", "\\(3:1\\).", "\\(4:1\\).", "\\(5:1\\).", "\\(6:1\\)."]}, {"statement": "<img alt=\"Figure 10\" src=\"artifact/paper-2/1986/figure/10.svg\"/><br/>In the figure, \\(ABCD\\) is a straight line with \\(AB=BC=CD\\). Three circles I, II and III are drawn respectively on \\(AB\\), \\(AC\\) and \\(AD\\) as diameters. Areas of circle I : Area of circle II : Area of circle III =", "options": ["\\(1:2:3\\).", "\\(1:2:4\\).", "\\(1:4:9\\).", "\\(1:4:16\\).", "\\(1:8:27\\)."]}, {"statement": "Aman drives a car at \\(45\\text{ km/h}\\) for \\(3\\) hours and then at \\(50\\text{ km/h}\\) for \\(2\\) hours. His average speed for the whole journey is", "options": ["\\(47\\text{ km/h}\\).", "\\(47.5\\text{ km/h}\\).", "\\(48\\text{ km/h}\\).", "\\(48.5\\text{ km/h}\\).", "\\(49\\text{ km/h}\\)."]}, {"statement": "<img alt=\"Figure 12a\" src=\"artifact/paper-2/1986/figure/12a.svg\"/> <img alt=\"Figure 12b\" src=\"artifact/paper-2/1986/figure/12b.svg\"/><br/>In the figure, if \\(\\dfrac{\\text{Volume of the sphere}}{\\text{Volume of the right circular cylinder}}=\\dfrac{9}{2}\\), then \\(\\dfrac{R}{r}=\\)", "options": ["\\(\\dfrac{3}{2}\\).", "\\(\\dfrac{3}{\\sqrt{2}}\\).", "\\(???\\).", "\\(\\dfrac{\\sqrt[3]{9}}{\\sqrt[3]{2}}\\).", "\\(\\dfrac{9}{2}\\)."]}, {"statement": "If the compound interest on \\( \\$ 1000 \\) for two years at \\(9\\%\\) p.a., pay half-yearly is \\(\\$x\\), find \\(x\\).", "options": ["\\(1000\\times\\dfrac{9}{100}\\times2\\)", "\\(1000\\left(1+\\dfrac{9}{100}\\right)^4\\)", "\\(1000\\left(1+\\dfrac{4.5}{100}\\right)^4\\)", "\\(1000\\left(1+\\dfrac{9}{100}\\right)^2-1000\\)", "\\(1000\\left(1+\\dfrac{4.5}{100}\\right)^4-1000\\)"]}, {"statement": "If \\(\\sin\\theta\\cos\\theta=\\dfrac{1}{4}\\), then \\((\\sin\\theta+\\cos\\theta)^2=\\)", "options": ["\\(2\\).", "\\(\\dfrac{3}{2}\\).", "\\(1\\).", "\\(\\dfrac{1}{2}\\).", "\\(\\dfrac{1}{4}\\)."]}, {"statement": "<img alt=\"Figure 15\" src=\"artifact/paper-2/1986/figure/15.svg\"/><br/>Which of the following functions may be represented by the above graph in the interval \\(0\\) to \\(2\\pi\\)?", "options": ["\\(y=\\cos2x\\)", "\\(y=2\\cos x\\)", "\\(y=\\dfrac{1}{2}\\cos2x\\)", "\\(y=\\sin2x\\)", "\\(y=2\\sin2x\\)"]}, {"statement": "\\(\\sin^4\\theta-\\cos^4\\theta=\\)", "options": ["\\(-1\\).", "\\(1-2\\cos^4\\theta\\).", "\\(\\sin\\theta-\\cos\\theta\\).", "\\(\\sin^2\\theta-\\cos^2\\theta\\).", "\\(2\\sin^4\\theta-1\\)."]}, {"statement": "<img alt=\"Figure 17\" src=\"artifact/paper-2/1986/figure/17.svg\"/><br/>In the figure, \\(\\angle A:\\angle B:\\angle C=\\)", "options": ["\\(2:\\sqrt{3}:1\\).", "\\(4:3:1\\).", "\\(3:2:1\\).", "\\(\\sqrt{3}:\\sqrt{2}:1\\).", "\\(1:2:\\sqrt{3}\\)."]}, {"statement": "<img alt=\"Figure 18\" src=\"artifact/paper-2/1986/figure/18.svg\"/><br/>In the figure, if the area of the sector is \\(x\\), then arc \\(ACB=\\)", "options": ["\\(\\dfrac{2x}{r}\\).", "\\(\\dfrac{x}{r}\\).", "\\(\\dfrac{2x}{r^2}\\).", "\\(\\dfrac{\\pi x}{90r}\\).", "\\(\\dfrac{90x}{\\pi r}\\)."]}, {"statement": "<img alt=\"Figure 19\" src=\"artifact/paper-2/1986/figure/19.svg\"/><br/>In the figure, \\(AC=AD=1\\). \\(\\angle ABD=20^\\circ\\) and \\(\\angle CAD=120^\\circ\\), find \\(AB\\).", "options": ["\\(2\\cos20^\\circ\\)", "\\(\\dfrac{1}{2\\sin20^\\circ}\\)", "\\(\\dfrac{\\sqrt{3}}{2\\sin20^\\circ}\\)", "\\(\\sqrt{3}\\cos20^\\circ\\)", "\\(2\\sin20^\\circ\\)"]}, {"statement": "The bearing of a lighthouse as observed from an ocean liner is \\(\\text{N} 37^\\circ\\text{E}\\), the bearing of the ocean liner as observed from the lighthouse is", "options": ["\\(\\text{N} 37^\\circ\\text{E}\\).", "\\(\\text{N} 53^\\circ\\text{W}\\).", "\\(\\text{S} 37^\\circ\\text{E}\\).", "\\(\\text{S} 37^\\circ\\text{W}\\).", "\\(\\text{S} 53^\\circ\\text{W}\\)."]}, {"statement": "Which of the following represents a circle?", "options": ["\\(2x^2-8y+5=0\\)", "\\(2x^2+y^2-4x-3y=0\\)", "\\(3x^2+3y^2-5x-7=0\\)", "\\(x^2-y^2-7x+6y+1=0\\)", "\\(x^2+y^2+2xy+7y-1=0\\)"]}, {"statement": "<img alt=\"Figure 22\" src=\"artifact/paper-2/1986/figure/22.svg\"/><br/>In the figure, \\(L_1\\) and \\(L_2\\) are two straight lines perpendicular to each other and intersecting at \\(P\\) on the \\(y\\)-axis. If the equation of \\(L_1\\) is \\(y=ax-5\\), then the equation of \\(L_2\\) is", "options": ["\\(y=-\\dfrac{1}{a}x-5\\).", "\\(y=-\\dfrac{1}{a}+5\\).", "\\(y=-ax-5\\).", "\\(y=-ax+5\\).", "\\(y=-\\dfrac{1}{a}x\\)."]}, {"statement": "<img alt=\"Figure 23\" src=\"artifact/paper-2/1986/figure/23.svg\"/><br/>In the figure, \\(x=\\)", "options": ["\\(77^\\circ\\).", "\\(84^\\circ\\).", "\\(96^\\circ\\).", "\\(103^\\circ\\).", "\\(115^\\circ\\)."]}, {"statement": "<img alt=\"Figure 24\" src=\"artifact/paper-2/1986/figure/24.svg\"/><br/>In the figure, \\(ABC\\), \\(ACD\\), \\(ADE\\) and \\(AEF\\) are right angled isosceles triangles. If \\(AB=BC=1\\), how long is \\(AF\\)?", "options": ["\\(2\\sqrt{5}\\)", "\\(4\\)", "\\(2\\sqrt{3}\\)", "\\(3\\)", "\\(\\sqrt{5}\\)"]}, {"statement": "<img alt=\"Figure 25\" src=\"artifact/paper-2/1986/figure/25.svg\"/><br/>In the figure, \\(A, B, C, D\\) and \\(E\\) lie on a circle. \\(AC\\) intersects \\(BE\\) at \\(K\\). \\(\\angle ACD=100^\\circ\\) and \\(\\angle CDE=130^\\circ\\). If \\(BE \\mathbin{\\!/\\mkern-5mu/\\!} CD\\), then \\(\\angle ACB=\\)", "options": ["\\(25^\\circ\\).", "\\(30^\\circ\\).", "\\(36^\\circ\\).", "\\(40^\\circ\\).", "\\(42^\\circ\\)."]}, {"statement": "In a shooting game, the probabilities for John and Mary to hit a target are \\(\\dfrac{4}{5}\\) and \\(\\dfrac{3}{5}\\) respectively. When both shoot at the target, what is the probability that they both miss?", "options": ["\\(\\dfrac{2}{25}\\)", "\\(\\dfrac{3}{25}\\)", "\\(\\dfrac{8}{25}\\)", "\\(\\dfrac{12}{25}\\)", "\\(\\dfrac{13}{25}\\)"]}, {"statement": "Given two groups of numbers \\(a+1, a+2, a+3\\) and \\(b+1, b+2, b+3\\), where \\(a \\gt b\\). \\(m_1\\) and \\(m_2\\) are respectively the means of the two groups, and \\(s_1\\) and \\(s_2\\) are respectively their standard deviations. Which of the following is true?", "options": ["\\(m_1 \\gt m_2\\) and \\(s_1 \\gt s_2\\)", "\\(m_1 \\gt m_2\\) and \\(s_1 = s_2\\)", "\\(m_1 = m_2\\) and \\(s_1 \\gt s_2\\)", "\\(m_1 = m_2\\) and \\(s_1 = s_2\\)", "\\(m_1 \\gt m_2\\) and \\(s_1 \\lt s_2\\)"]}, {"statement": "<img alt=\"Figure 28a\" src=\"artifact/paper-2/1986/figure/28a.svg\"/><br/>The figure shows the frequency curve of a certain distribution. Which of the following can be the distribution's cumulative frequency curve?", "options": ["<img alt=\"Figure 28b\" src=\"artifact/paper-2/1986/figure/28b.svg\"/>", "<img alt=\"Figure 28c\" src=\"artifact/paper-2/1986/figure/28c.svg\"/>", "<img alt=\"Figure 28d\" src=\"artifact/paper-2/1986/figure/28d.svg\"/>", "<img alt=\"Figure 28e\" src=\"artifact/paper-2/1986/figure/28e.svg\"/>", "<img alt=\"Figure 28f\" src=\"artifact/paper-2/1986/figure/28f.svg\"/>"]}, {"statement": "If \\((10^x)^y=(2^z)(5^z)\\), then which of the following must be true", "options": ["\\(xy=z\\).", "\\(xy=2z\\).", "\\(xy=z^2\\).", "\\(x^y=z\\).", "\\(x^y=2z\\)."]}, {"statement": "\\(\\left(\\sqrt{\\dfrac{x}{y}}+\\sqrt{\\dfrac{y}{x}}\\right)^2=\\)", "options": ["\\(\\dfrac{(x+y)^2}{xy}\\).", "\\(\\dfrac{x^2+y^2}{xy}\\).", "\\(\\dfrac{x+y+2}{xy}\\).", "\\(\\dfrac{x+y}{xy}\\).", "\\(1\\)."]}, {"statement": "The L.C.M. of \\(12a^2b\\) and \\(18ab^3c\\) is", "options": ["\\(6ab\\).", "\\(6a^2b^3c\\).", "\\(36ab\\).", "\\(36a^2b^3c\\).", "\\(216a^3b^4c\\)."]}, {"statement": "<img alt=\"Figure 32\" src=\"artifact/paper-2/1986/figure/32.svg\"/><br/>Let \\(p=2x+3y\\). Under the following constraints<br/>\\(\\begin{cases} x \\ge 0 \\\\ y \\ge 0 \\\\ x \\le 4 \\\\ y \\le 3 \\\\ x+y \\le 6 \\end{cases}\\)<br/>what is the greatest value of \\(p\\)?", "options": ["\\(8\\)", "\\(14\\)", "\\(15\\)", "\\(16\\)", "\\(17\\)"]}, {"statement": "If \\(\\log x^2+\\log y^2=\\log z^2\\), where \\(x\\), \\(y\\) and \\(z\\) are positive numbers, which of the following must be true?<br/>I. \\(x^2+y^2=z^2\\).<br/>II. \\(\\log x+\\log y=\\log z\\)<br/>III. \\(x^2y^2=z^2\\)", "options": ["I only", "II only", "III only", "I and II only", "II and III only"]}, {"statement": "Let \\(F(x)=2x^3+3x^2-11x-6\\). Given that \\(F(2)=0\\) and \\(F(-3)=0\\), then \\(F(x)\\) can be factorized as", "options": ["\\((x+2)(x-3)(2x+1)\\).", "\\((x+2)(x-3)(2x-1)\\).", "\\((x-2)(x+3)(2x+1)\\).", "\\((x-2)(x-3)(2x+1)\\).", "\\((x-2)(x+3)(2x-1)\\)."]}, {"statement": "If \\(a\\), \\(b\\) and \\(c\\) are positive numbers, which of the following is a possible graphical representation of \\(y=ax^2+bx+c\\)?", "options": ["<img src=\"artifact/paper-2/1986/figure/35a.svg\"/>", "<img src=\"artifact/paper-2/1986/figure/35b.svg\"/>", "<img src=\"artifact/paper-2/1986/figure/35c.svg\"/>", "<img src=\"artifact/paper-2/1986/figure/35d.svg\"/>", "<img src=\"artifact/paper-2/1986/figure/35e.svg\"/>"]}, {"statement": "If \\(a \\gt 0\\) and \\(b \\lt 0\\), which of the following is/are negative?<br/>I. \\(\\dfrac{1}{a}-\\dfrac{1}{b}\\)<br/>II. \\(\\dfrac{a}{b}+\\dfrac{b}{a}\\)<br/>III. \\(\\dfrac{a^2}{b}-\\dfrac{b^2}{a}\\)", "options": ["I only", "III only", "I and II only", "I and III only", "II and III only"]}, {"statement": "If \\(2 \\lt x \\lt 3\\) and \\(3 \\lt y \\lt 4\\), then the range of values of \\(\\dfrac{x}{y}\\) is", "options": ["\\(\\dfrac{1}{2} \\lt \\dfrac{x}{y} \\lt \\dfrac{3}{4}\\).", "\\(\\dfrac{1}{2} \\lt \\dfrac{x}{y} \\lt 1\\).", "\\(\\dfrac{2}{3} \\lt \\dfrac{x}{y} \\lt \\dfrac{3}{4}\\).", "\\(\\dfrac{2}{3} \\lt \\dfrac{x}{y} \\lt 1\\).", "\\(\\dfrac{4}{3} \\lt \\dfrac{x}{y} \\lt \\dfrac{3}{2}\\)."]}, {"statement": "<img alt=\"Figure 38\" src=\"artifact/paper-2/1986/figure/38.svg\"/><br/>\\(ABCDEFGH\\) is a cube of side \\(3\\text{ cm}\\). A tetrahedron \\(DACH\\) is cut away along the plane \\(ACH\\). The volume of the remaining solid is", "options": ["\\(6\\text{ cm}^3\\).", "\\(9\\text{ cm}^3\\).", "\\(13.5\\text{ cm}^3\\).", "\\(18\\text{ cm}^3\\).", "\\(22.5\\text{ cm}^3\\)."]}, {"statement": "The marked price of an article is originally \\(P\\). The marked price is then increased so that when a discount of \\(10\\%\\) is made on the new marked price, the selling price is still \\(P\\). What is the new marked price?", "options": ["\\(\\dfrac{9}{10}P\\)", "\\(\\dfrac{109}{100}P\\)", "\\(\\dfrac{11}{10}P\\)", "\\(\\dfrac{111}{100}P\\)", "\\(\\dfrac{10}{9}P\\)"]}, {"statement": "<img alt=\"Figure 40\" src=\"artifact/paper-2/1986/figure/40.svg\"/><br/>The total surface area of a regular tetrahedron of side \\(3\\text{ cm}\\) is", "options": ["\\(\\dfrac{9\\sqrt{3}}{4}\\text{ cm}^2\\).", "\\(9\\text{ cm}^2\\).", "\\(\\dfrac{27\\sqrt{3}}{4}\\text{ cm}^2\\).", "\\(9\\sqrt{3}\\text{ cm}^2\\).", "\\(12\\sqrt{3}\\text{ cm}^2\\)."]}, {"statement": "Ten litres of a mixture contain \\(60\\%\\) of alcohol and \\(40\\%\\) of water by volume. How many litres of water should be added so that it contains \\(30\\%\\) of alcohol by volume?", "options": ["\\(5\\)", "\\(10\\)", "\\(15\\)", "\\(20\\)", "\\(30\\)"]}, {"statement": "If \\(A\\), \\(B\\), and \\(C\\) can finish running the same distance in \\(3\\), \\(4\\) and \\(5\\) minutes respectively, then \\(A\\)'s speed : \\(B\\)'s speed : \\(C\\)'s speed =", "options": ["\\(3:4:5\\).", "\\(5:4:3\\).", "\\(9:8:7\\).", "\\(20:15:12\\).", "\\(25:16:9\\)."]}, {"statement": "If the five interior angles of a convex pentagon form an A.P. with a common difference of \\(10^\\circ\\), then the smallest interior angle of the pentagon is", "options": ["\\(52^\\circ\\).", "\\(72^\\circ\\).", "\\(88^\\circ\\).", "\\(98^\\circ\\).", "\\(108^\\circ\\)."]}, {"statement": "Let \\(p\\) be a positive constant such that \\(p\\sin\\theta=\\sqrt{3}\\) and \\(p\\cos\\theta=1\\). Find all the values of \\(\\theta\\) in the interval \\(0\\) to \\(2\\pi\\).", "options": ["\\(\\dfrac{\\pi}{3}\\)", "\\(\\dfrac{\\pi}{6}\\)", "\\(\\dfrac{\\pi}{3}, \\dfrac{4\\pi}{3}\\)", "\\(\\dfrac{\\pi}{6}, \\dfrac{7\\pi}{6}\\)", "Cannot be determined"]}, {"statement": "<img alt=\"Figure 45\" src=\"artifact/paper-2/1986/figure/45.svg\"/><br/>In \\(\\Delta ABC\\), \\(AB=2\\), \\(AC=3\\) and \\(\\sin B=\\dfrac{3}{4}\\), then \\(\\cos^2 C=\\)", "options": ["\\(\\dfrac{9}{16}\\).", "\\(\\dfrac{9}{13}\\).", "\\(\\dfrac{1}{4}\\).", "\\(\\dfrac{1}{2}\\).", "\\(\\dfrac{3}{4}\\)."]}, {"statement": "<img alt=\"Figure 46\" src=\"artifact/paper-2/1986/figure/46.svg\"/><br/>In the figure, \\(BD:DC=\\)", "options": ["\\(\\sin C:\\sin B\\).", "\\(\\cos C:\\cos B\\).", "\\(\\tan C:\\tan B\\).", "\\(\\sin B:\\sin C\\).", "\\(\\cos B:\\cos C\\)."]}, {"statement": "<img alt=\"Figure 47\" src=\"artifact/paper-2/1986/figure/47.svg\"/><br/>In the figure, \\(ABCD\\) is a square. Arcs \\(AC\\) and \\(BD\\) are drawn with centres \\(D\\) and \\(C\\) respectively, intersecting at \\(O\\). Arc \\(AO : \\text{Arc } OC=\\)", "options": ["\\(1:\\sqrt{2}\\).", "\\(1:\\sqrt{3}\\).", "\\(1:2\\).", "\\(1:3\\).", "\\(2:3\\)."]}, {"statement": "<img alt=\"Figure 48\" src=\"artifact/paper-2/1986/figure/48.svg\"/><br/>In the figure, \\(ABCD\\) and \\(EFGH\\) are two squares of side \\(1\\). They are placed one upon the other with their centres both at \\(O\\) to form a star with \\(16\\) sides, each of length \\(x\\). Find \\(x\\).", "options": ["\\(\\dfrac{2}{7}\\)", "\\(\\dfrac{1}{3}\\)", "\\(\\dfrac{2}{5}\\)", "\\(\\dfrac{1}{2+\\sqrt{2}}\\)", "\\(\\dfrac{1}{1+\\sqrt{2}}\\)"]}, {"statement": "<img alt=\"Figure 49\" src=\"artifact/paper-2/1986/figure/49.svg\"/><br/>\\(DA\\) and \\(DC\\) are equal chords of the circle \\(ABCD\\). \\(\\angle CDB=40^\\circ\\) and \\(\\angle DAB=100^\\circ\\). \\(\\angle ADB=\\)", "options": ["\\(20^\\circ\\).", "\\(25^\\circ\\).", "\\(30^\\circ\\).", "\\(35^\\circ\\).", "\\(40^\\circ\\)."]}, {"statement": "<img alt=\"Figure 50\" src=\"artifact/paper-2/1986/figure/50.svg\"/><br/>In the figure, \\(AB\\) and \\(AC\\) are tangents to the circle \\(BCD\\). If \\(\\angle BDC=50^\\circ\\), then \\(\\angle A=\\)", "options": ["\\(130^\\circ\\).", "\\(100^\\circ\\).", "\\(85^\\circ\\).", "\\(80^\\circ\\).", "\\(50^\\circ\\)."]}, {"statement": "<img alt=\"Figure 51\" src=\"artifact/paper-2/1986/figure/51.svg\"/><br/>In \\(\\Delta ABC\\), \\(AP=3\\), \\(AQ=6\\) and \\(QC=4\\). If \\(\\angle APQ=\\angle ACB\\), then \\(PB=\\)", "options": ["\\(7\\).", "\\(8\\).", "\\(10\\).", "\\(17\\).", "\\(20\\)."]}, {"statement": "<img alt=\"Figure 52\" src=\"artifact/paper-2/1986/figure/52.svg\"/><br/>Three circles, centres \\(A\\), \\(B\\) and \\(C\\) touch each other as shown in the figure. The radii of the two circles with centre \\(A\\) and \\(B\\) are both \\(1\\text{ cm}\\) and radius of the circle with centre \\(C\\) is \\(3\\text{ cm}\\). Find the area of the shaded part in \\(\\text{ cm}^2\\).", "options": ["\\(\\sqrt{3}-\\dfrac{\\pi}{3}\\)", "\\(\\sqrt{3}-\\dfrac{\\pi}{6}\\)", "\\(2\\sqrt{3}-\\dfrac{\\pi}{3}\\)", "\\(2\\sqrt{3}-\\dfrac{\\pi}{6}\\)", "It cannot be determined"]}, {"statement": "<img alt=\"Figure 53\" src=\"artifact/paper-2/1986/figure/53.svg\"/><br/>A circle, centre \\(O\\), touches the sector \\(ABC\\) internally at \\(D\\), \\(E\\) and \\(F\\). \\(\\angle C=60^\\circ\\) and \\(AC=18\\). Find the radius of the circle.", "options": ["\\(9\\)", "\\(6\\)", "\\(5\\)", "\\(4\\)", "\\(3\\)"]}, {"statement": "<img alt=\"Figure 54\" src=\"artifact/paper-2/1986/figure/54.svg\"/><br/>In the figure, \\(PQ\\) is a diameter and \\(PT\\) is a tangent of the circle. \\(QT\\) cuts the circle at \\(R\\). Let \\(\\angle Q=\\theta\\) and \\(PQ=x\\), then \\(TR=\\)", "options": ["\\(\\dfrac{x}{\\cos\\theta}\\).", "\\(\\dfrac{x}{\\sin\\theta}\\).", "\\(\\dfrac{x}{\\sin\\theta\\tan\\theta}\\).", "\\(x\\sin\\theta\\tan\\theta\\).", "\\(x\\cos\\theta\\tan\\theta\\)."]}]